caesium/__init__.py
caesium/compressor.py
caesium/downloader.py
caesium_image_compressor-0.19.3.dist-info/LICENSE
caesium_image_compressor-0.19.3.dist-info/METADATA
caesium_image_compressor-0.19.3.dist-info/WHEEL
caesium_image_compressor-0.19.3.dist-info/entry_points.txt
caesium_image_compressor-0.19.3.dist-info/top_level.txt
caesium_image_compressor-0.19.3.dist-info/RECORD
