Metadata-Version: 2.1
Name: caesium_image_compressor
Version: 0.19.3
Summary: Caesium Image Compressor Wrapper For Python
Author-email: Brian Jemilo II <jemiloii@gmail.com>
License: Apache License
Project-URL: Homepage, https://github.com/jemiloii/caesium_image_compressor
Keywords: caesium,image,compressor,reducer,wrapper
Classifier: License :: OSI Approved :: Apache Software License
Classifier: Programming Language :: Python
Classifier: Programming Language :: Python :: 3
Requires-Python: >=3.10
License-File: LICENSE
